pyrosetta-installer/__init__.py
pyrosetta_installer/__init__.py
pyrosetta_installer-0.1.2.dist-info/METADATA
pyrosetta_installer-0.1.2.dist-info/WHEEL
pyrosetta_installer-0.1.2.dist-info/top_level.txt
pyrosetta_installer-0.1.2.dist-info/RECORD
