Metadata-Version: 2.1
Name: pyrosetta-installer
Version: 0.1.2
Summary: Download PyRosetta wheel package from PyRosetta.org and install it
Home-page: https://www.pyrosetta.org/
Author: Sergey Lyskov
License: Rosetta Software License
